pyclarity_values/__init__.py
pyclarity_values/bytes_reader.py
pyclarity_values/clarity_value.py
pyclarity_values/common.py
pyclarity_values/constants.py
pyclarity_values/deserialize.py
pyclarity_values/serialize.py
pyclarity_values/type_boolean_cv.py
pyclarity_values/type_buffer_cv.py
pyclarity_values/type_int_cv.py
pyclarity_values/type_list_cv.py
pyclarity_values/type_optional_cv.py
pyclarity_values/type_principal_cv.py
pyclarity_values/type_response_cv.py
pyclarity_values/type_string_cv.py
pyclarity_values/type_tuple_cv.py
pyclarity_values-0.1.0.dist-info/licenses/LICENSE
pyclarity_values-0.1.0.dist-info/METADATA
pyclarity_values-0.1.0.dist-info/WHEEL
pyclarity_values-0.1.0.dist-info/top_level.txt
pyclarity_values-0.1.0.dist-info/RECORD
