Metadata-Version: 2.4
Name: pyclarity-values
Version: 0.1.0
Summary: Work with Clarity smart contract values in Python
Author-email: Oleksii Opanasiuk <oo@allbridge.io>
License: MIT
Project-URL: Homepage, https://github.com/allbridge-io/pyclarity-values
License-File: LICENSE
Dynamic: license-file
